Metadata-Version: 1.0
Name: pyepub
Version: 0.5.0
Summary: Enhanced EPUB library
Home-page: https://github.com/Gluejar/pyepub
Author: Gabriele Alese, Eric Hellman
Author-email: eric@hellman.net
License: MIT
Platform: UNKNOWN
